pymathematics/__init__.py
pymathematics/info.py
pymathematics/main.py
pymathematics-2023.5.13.1.dist-info/LICENSE
pymathematics-2023.5.13.1.dist-info/METADATA
pymathematics-2023.5.13.1.dist-info/WHEEL
pymathematics-2023.5.13.1.dist-info/top_level.txt
pymathematics-2023.5.13.1.dist-info/RECORD
