Metadata-Version: 2.1
Name: pymathematics
Version: 2023.5.13.1
Summary: package for mathematics
Home-page: https://github.com/Sahil-Rajwar-2004/pymathematics
Author: Sahil Rajwar
Author-email: justsahilrajwar2004@gmail.com
Maintainer: its_Sahil
License: MIT
Keywords: maths,mathematics
Platform: UNKNOWN
Classifier: Programming Language :: Python :: 3
Classifier: Intended Audience :: Education
Classifier: Operating System :: OS Independent
License-File: LICENSE
Requires-Dist: sympy
